JHFDRONE/JHFDRONE.py
JHFDRONE/__init__.py
JHFDRONE/enumHelper.py
JHFDRONE/peripheral.py
JHFDRONE/serialHelper.py
jhfdrone-0.0.4.dist-info/LICENSE
jhfdrone-0.0.4.dist-info/METADATA
jhfdrone-0.0.4.dist-info/WHEEL
jhfdrone-0.0.4.dist-info/top_level.txt
jhfdrone-0.0.4.dist-info/RECORD
