Metadata-Version: 2.1
Name: JHFDRONE
Version: 0.0.4
Summary: A python package for JHF Drone control
Author-email: chenghao <chenghao.wang@uphf.fr>
Classifier: Programming Language :: Python :: 3
Classifier: Programming Language :: Python :: 3.7
Classifier: Programming Language :: Python :: 3.8
Classifier: Programming Language :: Python :: 3.9
Classifier: Programming Language :: Python :: 3.10
Classifier: Programming Language :: Python :: 3.11
Classifier: License :: OSI Approved :: MIT License
Classifier: Operating System :: OS Independent
Requires-Python: >=3.7
License-File: LICENSE
Requires-Dist: strenum
Requires-Dist: pyserial
